scrapy_h5/__init__.py
scrapy_h5/extractor.py
scrapy_h5/extractor_test.py
scrapy_h5/integration_test.py
scrapy_h5/middleware.py
scrapy_h5/middleware_test.py
scrapy_h5/response.py
scrapy_h5/selector.py
scrapy_h5/selector_test.py
scrapy_h5-0.5.1.dist-info/METADATA
scrapy_h5-0.5.1.dist-info/WHEEL
scrapy_h5-0.5.1.dist-info/top_level.txt
scrapy_h5-0.5.1.dist-info/RECORD
