Metadata-Version: 2.4
Name: scrapy-h5
Version: 0.5.1
Summary: Scrapy HTML5 support
Requires-Python: >=3.10
Requires-Dist: markupever>=0.3.2
Requires-Dist: parsel>=1.10.0
Requires-Dist: scrapy>=2.14.1
Requires-Dist: selectolax>=0.4.6
Requires-Dist: w3lib>=2.3.1
